.DS_Store
nclustgen/BiclusterGen.py
nclustgen/Generator.py
nclustgen/TriclusterGen.py
nclustgen/__init__.py
nclustgen/utils.py
nclustgen/jars/.DS_Store
nclustgen/jars/G-Bic-1.0.0.jar
nclustgen/jars/G-Tric-1.0.2.jar
tests/__init__.py
tests/main_test.py
nclustgen-1.0.4.dist-info/LICENSE
nclustgen-1.0.4.dist-info/METADATA
nclustgen-1.0.4.dist-info/WHEEL
nclustgen-1.0.4.dist-info/top_level.txt
nclustgen-1.0.4.dist-info/RECORD
