Metadata-Version: 2.1
Name: nclustgen
Version: 1.0.4
Summary: Tool to generate biclustering and triclustering datasets
Home-page: https://github.com/PedroCotovio/nclustgen
Author: Pedro Cotovio
Author-email: pgcotovio@gmail.com
License: GNU GPLv3
Project-URL: Bug Tracker, https://github.com/PedroCotovio/nclustgen/issues
Project-URL: Documentation, https://nclustgen.readthedocs.org
Keywords: biclustring triclustering generator data nclustgen
Platform: UNKNOWN
Classifier: Programming Language :: Python :: 3.8
Classifier: Programming Language :: Python :: 3.7
Classifier: License :: OSI Approved :: GNU General Public License v3 (GPLv3)
Classifier: Natural Language :: English
Classifier: Operating System :: MacOS :: MacOS X
Classifier: Operating System :: Microsoft :: Windows
Classifier: Operating System :: Unix
Classifier: Intended Audience :: Information Technology
Classifier: Intended Audience :: Science/Research
Classifier: Topic :: Scientific/Engineering :: Artificial Intelligence
Classifier: Topic :: Scientific/Engineering :: Bio-Informatics
Requires-Python: >=3.7
Requires-Dist: dgl (>=0.6.1)
Requires-Dist: JPype1 (>=1.2.1)
Requires-Dist: networkx (>=2.5.1)
Requires-Dist: torch (>=1.8.1)
Requires-Dist: numpy
Requires-Dist: scipy
Requires-Dist: sparse
